agenthub_tools/core/__init__.py
agenthub_tools/core/base.py
agenthub_tools_core-0.0.7.dist-info/METADATA
agenthub_tools_core-0.0.7.dist-info/WHEEL
agenthub_tools_core-0.0.7.dist-info/top_level.txt
agenthub_tools_core-0.0.7.dist-info/RECORD
