Metadata-Version: 2.1
Name: agenthub-tools-core
Version: 0.0.7
Summary: AgentHub core package
Author-email: Jacob Weiss <jaweiss2305@gmail.com>
Project-URL: homepage, https://github.com/jacobweiss2305/agenthub-tools
Project-URL: repository, https://github.com/jacobweiss2305/agenthub-tools/tree/main/packages/core
Requires-Python: >=3.7
